probjax/__init__.py
probjax/core/__init__.py
probjax/core/transformation.py
probjax/core/custom_primitives/__init__.py
probjax/core/custom_primitives/custom_inverse.py
probjax/core/custom_primitives/random_variable.py
probjax/core/interpreters/__init__.py
probjax/core/interpreters/constraints.py
probjax/core/interpreters/interventions.py
probjax/core/interpreters/inverse.py
probjax/core/interpreters/joint_sample.py
probjax/core/interpreters/log_potential.py
probjax/core/interpreters/symbolic.py
probjax/core/interpreters/trace.py
probjax/core/jaxpr_propagation/__init__.py
probjax/core/jaxpr_propagation/graph.py
probjax/core/jaxpr_propagation/interpret.py
probjax/core/jaxpr_propagation/propagate.py
probjax/core/jaxpr_propagation/utils.py
probjax/distributions/__init__.py
probjax/distributions/constraint_registry.py
probjax/distributions/constraints.py
probjax/distributions/continuous.py
probjax/distributions/discrete.py
probjax/distributions/distribution.py
probjax/distributions/exponential_family.py
probjax/distributions/independent.py
probjax/distributions/mixture.py
probjax/distributions/sde.py
probjax/distributions/transformed_distribution.py
probjax/distributions/truncated_distribution.py
probjax/distributions/utils.py
probjax/distributions/divergences/__init__.py
probjax/distributions/divergences/divergence.py
probjax/distributions/divergences/kl.py
probjax/distributions/divergences/wasserstein.py
probjax/inference/__init__.py
probjax/inference/filter.py
probjax/inference/mcmc.py
probjax/inference/rejection.py
probjax/inference/smc.py
probjax/inference/filtering/__init__.py
probjax/inference/filtering/base.py
probjax/inference/filtering/kalman_filter.py
probjax/inference/filtering/kalman_filter_old.py
probjax/inference/filtering/particle_filter.py
probjax/inference/filtering/uncented_kalman_filter.py
probjax/inference/kernels/__init__.py
probjax/inference/kernels/adaptation.py
probjax/inference/kernels/base.py
probjax/inference/kernels/dynamic_hmc.py
probjax-0.1.0.dist-info/LICENSE.txt
probjax-0.1.0.dist-info/METADATA
probjax-0.1.0.dist-info/WHEEL
probjax-0.1.0.dist-info/top_level.txt
probjax-0.1.0.dist-info/RECORD
