Metadata-Version: 2.1
Name: probjax
Version: 0.1.0
Summary: Jax library for probabilistic computations
Author-email: Manuel Gloeckler <manuel.gloeckler@uni-tuebingen.de>
License: MIT
Keywords: probabilistic,jax,computation
Classifier: License :: OSI Approved :: MIT License
Classifier: Intended Audience :: Developers
Classifier: Intended Audience :: Education
Classifier: Intended Audience :: Science/Research
Classifier: Operating System :: POSIX :: Linux
Classifier: Operating System :: MacOS :: MacOS X
Classifier: Programming Language :: Python
Classifier: Programming Language :: Python :: 3
Classifier: Programming Language :: Python :: 3.7
Classifier: Programming Language :: Python :: 3.8
Classifier: Programming Language :: Python :: 3.9
Requires-Python: >=3.9
License-File: LICENSE.txt
Requires-Dist: numpy>=2.1.2
Requires-Dist: matplotlib
Requires-Dist: jax>=0.4.34
Requires-Dist: jaxlib>=0.4.34
Requires-Dist: optax
Requires-Dist: ott-jax
Requires-Dist: networkx
Requires-Dist: blackjax
Requires-Dist: sympy
Provides-Extra: dev
Requires-Dist: pytest; extra == "dev"
Requires-Dist: ruff; extra == "dev"
Requires-Dist: pytest-xdist; extra == "dev"
